hastrofunc/__init__.py
hastrofunc/hastrofunc.py
hastrofunc-0.1.0.dist-info/LICENSE
hastrofunc-0.1.0.dist-info/METADATA
hastrofunc-0.1.0.dist-info/WHEEL
hastrofunc-0.1.0.dist-info/top_level.txt
hastrofunc-0.1.0.dist-info/RECORD
