Metadata-Version: 2.1
Name: hastrofunc
Version: 0.1.0
Summary: A package containing useful functions for astronomy research
Home-page: https://github.com/hvbish/hastrofunc
Author: Hannah Bish
Author-email: hvbish@uw.edu
Project-URL: Bug Tracker, https://github.com/hvbish/hastrofunc/issues
Classifier: Programming Language :: Python :: 3
Classifier: License :: OSI Approved :: MIT License
Classifier: Operating System :: OS Independent
Requires-Python: >=3.6
License-File: LICENSE
